inparse/__init__.py
inparse/inparse.py
inparse-0.1.1.dist-info/METADATA
inparse-0.1.1.dist-info/RECORD
inparse-0.1.1.dist-info/WHEEL
inparse-0.1.1.dist-info/top_level.txt
