Metadata-Version: 2.1
Name: inparse
Version: 0.1.1
Summary: Collaborative AI for  Web Scraping, Data Extraction and Crawling,Knowledge Graph 
Home-page: https://github.com/inparse/inparse
Author: Guojian Li
Author-email: guojianlee@gmail.com
License: BSD
Platform: UNKNOWN
Classifier: Development Status :: 3 - Alpha
Classifier: Intended Audience :: Developers
Classifier: License :: OSI Approved :: BSD License
Classifier: Programming Language :: Python :: 3
Requires-Python: >=3.6.5
Requires-Dist: requests
Requires-Dist: beautifulsoup4
Requires-Dist: lxml
